LICENSE
flask_smorest_sqla/__init__.py
flask_smorest_sqla/crud_blueprint.py
flask_smorest_sqla/utils.py
flask_smorest_sqla-0.2.2.dist-info/LICENSE
flask_smorest_sqla-0.2.2.dist-info/METADATA
flask_smorest_sqla-0.2.2.dist-info/WHEEL
flask_smorest_sqla-0.2.2.dist-info/RECORD
