Metadata-Version: 2.1
Name: flask-smorest-sqla
Version: 0.2.2
Summary: Adds SQLAlchemy support to a Flask-Smorest REST API
Home-page: https://github.com/zedrdave/flask-smorest-sqla
License: MIT
Author: Dave
Author-email: dave@tenko.ai
Requires-Python: >=3.9,<4.0
Classifier: License :: OSI Approved :: MIT License
Classifier: Programming Language :: Python :: 3
Classifier: Programming Language :: Python :: 3.9
Classifier: Programming Language :: Python :: 3.10
Classifier: Programming Language :: Python :: 3.11
Requires-Dist: flask-smorest (<1.0.0)
Requires-Dist: flask-sqlalchemy (>=3.0.3,<4.0.0)
Requires-Dist: marshmallow-sqlalchemy (>=0.29.0,<0.30.0)
Requires-Dist: sqlalchemy (>=2.0.7,<3.0.0)
